odfedit-2.19.dist-info/licenses/LICENSE.txt
src/OdfEdit.py
src/resources/BackgroundRegion.png
src/resources/BitmapNum.png
src/resources/EnclosureStyle.png
src/resources/GoObjectsTemplates.txt
src/resources/Help.txt
src/resources/HwObjectsAttributesCodes.txt
src/resources/HwObjectsAttributesDict.txt
src/resources/HwObjectsTypesList.txt
src/resources/ImageNumButton.png
src/resources/ImageNumLabel.png
src/resources/OdfEdit.ico
src/resources/OdfEdit.png
odfedit-2.19.dist-info/METADATA
odfedit-2.19.dist-info/WHEEL
odfedit-2.19.dist-info/top_level.txt
odfedit-2.19.dist-info/RECORD
