Metadata-Version: 2.4
Name: OdfEdit
Version: 2.19
Summary: Tool for GrandOrgue organ definition file edition and generation
Author: Eric Turpault
License:                     GNU GENERAL PUBLIC LICENSE
Keywords: organ,ODF,GrandOrgue,Hauptwerk
Requires-Python: >=3.10
License-File: LICENSE.txt
Requires-Dist: tkinter
Requires-Dist: sounddevice
Requires-Dist: audioplayer
Requires-Dist: pillow
Requires-Dist: lxml
Dynamic: license-file
